README
deluge_client_sync.py
setup.py
deluge_client_sync.egg-info/PKG-INFO
deluge_client_sync.egg-info/SOURCES.txt
deluge_client_sync.egg-info/dependency_links.txt
deluge_client_sync.egg-info/requires.txt
deluge_client_sync.egg-info/top_level.txt