Metadata-Version: 1.1
Name: deluge-client-sync
Version: 1.0.0
Summary: A synchronous API to deluge using normal python code (no TwistedMatrix, no asyncio)
Home-page: http://github.com/allseeingeyetolledewesew/deluge_client_sync
Author: AllSeeingEyeTolledEweSew
Author-email: allseeingeyetolledewesew@protonmail.com
License: Unlicense
Platform: UNKNOWN
Classifier: Development Status :: 5 - Production/Stable
Classifier: Intended Audience :: Developers
Classifier: License :: Public Domain
Classifier: Programming Language :: Python
Classifier: Topic :: Communications :: File Sharing
Classifier: Topic :: Software Development :: Libraries :: Python Modules
Classifier: Topic :: System :: Networking
Classifier: Operating System :: OS Independent
Classifier: License :: Public Domain
